solana_transfer/__init__.py
solana_transfer/client.py
solana_transfer-0.1.1.dist-info/METADATA
solana_transfer-0.1.1.dist-info/WHEEL
solana_transfer-0.1.1.dist-info/RECORD
